Metadata-Version: 2.1
Name: speedtest-http
Version: 0.0.6
Summary: Visualize data from speedtest_sampler in a web app
Home-page: https://github.com/shuntingyard/speedtest_http
Author: Tobias Frei
Author-email: shuntingard@gmail.com
License: mit
Platform: Linux
Classifier: Development Status :: 4 - Beta
Classifier: Programming Language :: Python
Classifier: Environment :: Web Environment
Classifier: Framework :: Flask
Classifier: Intended Audience :: End Users/Desktop
Classifier: Intended Audience :: System Administrators
Classifier: License :: OSI Approved :: MIT License
Classifier: Natural Language :: English
Classifier: Operating System :: POSIX :: Linux
Classifier: Programming Language :: Python :: 3.6
Classifier: Programming Language :: Python :: 3.7
Classifier: Topic :: System :: Networking
Requires-Python: >= 3.6
Provides-Extra: testing
